{"Category":[{"id":"27047","application_id":"994","parent_id":"0","title":"মেয়াদ বাড়ানোর উপায় (এয়ারটেল)","icon":null,"sort_weight":"1"},{"id":"27060","application_id":"994","parent_id":"27048","title":"প্লে প্যাকেজ করে পেতে পারেন","icon":null,"sort_weight":"1"},{"id":"27061","application_id":"994","parent_id":"27048","title":"২ জিবি মাত্র ৯ টাকায় পেতে","icon":null,"sort_weight":"1"},{"id":"27062","application_id":"994","parent_id":"27049","title":"শুধু মাত্র কোড ডায়াল করে পাবেন","icon":null,"sort_weight":"1"},{"id":"27063","application_id":"994","parent_id":"27049","title":"১ টাকা ৮০ পয়সা খরচ করে পাবেন","icon":null,"sort_weight":"1"},{"id":"27064","application_id":"994","parent_id":"27049","title":"Get 20MB with WOWBOX","icon":null,"sort_weight":"1"},{"id":"27065","application_id":"994","parent_id":"27049","title":"Online flexi plan নিয়ে","icon":null,"sort_weight":"1"},{"id":"27066","application_id":"994","parent_id":"27050","title":"রবি তে ডাটার মেয়াদ","icon":null,"sort_weight":"1"},{"id":"27067","application_id":"994","parent_id":"27050","title":"মোবাইলের টাইম তা বদলে দিন","icon":null,"sort_weight":"1"},{"id":"27068","application_id":"994","parent_id":"27051","title":"শুধুমাত্র ২২ টাকা রিচার্জে পেয়ে যাবেন","icon":null,"sort_weight":"1"},{"id":"27059","application_id":"994","parent_id":"27048","title":"ইন্টারনেট প্যাকে সাবস্ক্রাইব করে পাবেন","icon":null,"sort_weight":"1"},{"id":"27057","application_id":"994","parent_id":"0","title":"টাকা কেটে নেওয়া বন্ধ করার কোড","icon":null,"sort_weight":"1"},{"id":"27048","application_id":"994","parent_id":"0","title":"মেয়াদ বাড়ানোর উপায় (বাংলালিংক)","icon":null,"sort_weight":"1"},{"id":"27049","application_id":"994","parent_id":"0","title":"মেয়াদ বাড়ানোর উপায় (জিপি)","icon":null,"sort_weight":"1"},{"id":"27050","application_id":"994","parent_id":"0","title":"মেয়াদ বাড়ানোর উপায় (রবি)","icon":null,"sort_weight":"1"},{"id":"27051","application_id":"994","parent_id":"0","title":"মেয়াদ বাড়ানোর উপায় (টেলিটক)","icon":null,"sort_weight":"1"},{"id":"27052","application_id":"994","parent_id":"0","title":"গুরুত্বপূর্ন কোড (এয়ারটেল)","icon":null,"sort_weight":"1"},{"id":"27053","application_id":"994","parent_id":"0","title":"গুরুত্বপূর্ন কোড (বাংলালিংক)","icon":null,"sort_weight":"1"},{"id":"27054","application_id":"994","parent_id":"0","title":"গুরুত্বপূর্ন কোড (জিপি)","icon":null,"sort_weight":"1"},{"id":"27055","application_id":"994","parent_id":"0","title":"গুরুত্বপূর্ন কোড (রবি)","icon":null,"sort_weight":"1"},{"id":"27056","application_id":"994","parent_id":"0","title":"গুরুত্বপূর্ন কোড (টেলিটক)","icon":null,"sort_weight":"1"},{"id":"27069","application_id":"994","parent_id":"27051","title":"শুধুমাত্র ৩৮ টাকা রিচার্জে পেয়ে যাবেন","icon":null,"sort_weight":"1"}],"Collection":[{"id":"53200","category_id":"27047","descr":"\n<!DOCTYPE html>\n<html>\n<head>\n<meta charset = \"UTF-8\" >\n<style> \nh3{\ncolor:red;\n}\n<\/style> \n<\/head>\n<body>\n<h3 align=\"center\"><\/h3>\n<body bgcolor=\"#154360\">\n<body text=\"white\">\n<\/body>\n<\/html>\n\n<p style=\"text-align: center;\"><span style=\"font-size: 18pt; color: #ff0000;\">মেয়াদ বেড়ে যায় যেভাবে<\/span><\/p>\n<p><span style=\"font-size: 14pt;\">এয়ারটেল সিম এ <span style=\"color: #99cc00;\">MB<\/span> এর মেয়াদ বাড়ানো যায়<\/span><br \/><span style=\"font-size: 14pt;\">মেয়াদ শেষ হলে ও <span style=\"color: #99cc00;\">MB<\/span> গুলো থেকে যায়<\/span><br \/><span style=\"font-size: 14pt;\">মেয়াদ শেষ হয়ে গেলে এরপর তখন যদি নতুন করে <span style=\"color: #99cc00;\">MB<\/span> নেন তাহলে ঐ পুরনো <span style=\"color: #99cc00;\">MB<\/span> গুলো নতুন গুলোর সাথে যোগ হয়ে মেয়াদ বাড়িয়ে দিবে।<\/span><\/p>","answer":null,"total_up_vote":"0","total_down_vote":"0"},{"id":"53201","category_id":"27059","descr":"\n<!DOCTYPE html>\n<html>\n<head>\n<meta charset = \"UTF-8\" >\n<style> \nh3{\ncolor:red;\n}\n<\/style> \n<\/head>\n<body>\n<h3 align=\"center\"><\/h3>\n<body bgcolor=\"#154360\">\n<body text=\"white\">\n<\/body>\n<\/html>\n\n<p style=\"text-align: center;\"><span style=\"font-size: 18pt; color: #ff0000;\">ইন্টারনেট প্যাকে সাবস্ক্রাইব করে পাবেন<\/span><\/p>\n<p><span style=\"font-size: 14pt;\">যদি আপনি কোন ইন্টারনেট প্যাকে সার্সক্রাইব করা থাকে এবং ওই প্যাক চালু থাকে ও ব্যালেন্সে পযাপ্ত টাকা থাকে তবে মেয়াত বাড়াতে হবে না ।<\/span><br \/><span style=\"font-size: 14pt;\">ওই প্যাক এঠ মেয়াদ শেষ হলে আবার <span style=\"color: #99cc00;\">rewal<\/span> হয়ে আগের ব্যালেন্সের সাথে এমবি যোগ হবে । আর যদি আপনি <span style=\"color: #99cc00;\">unsciribe<\/span> করেন তাহলে এমবির মেয়াদ বাড়ানো যাবে না ।<\/span><br \/><span style=\"font-size: 14pt;\">তাই নিয়মিত ইন্টারনেট প্যাক সার্সক্রাইব করে থাকুন আর ইন্টারনেট চালাতে থাকুন । আপনার ইন্টারনেট এর ফুল ভলিউম দেখতে <span style=\"color: #99cc00;\">*৫০০০*৫০০#<\/span> ডায়াল করুন ।<\/span><\/p>","answer":null,"total_up_vote":"0","total_down_vote":"0"},{"id":"53202","category_id":"27060","descr":"\n<!DOCTYPE html>\n<html>\n<head>\n<meta charset = \"UTF-8\" >\n<style> \nh3{\ncolor:red;\n}\n<\/style> \n<\/head>\n<body>\n<h3 align=\"center\"><\/h3>\n<body bgcolor=\"#154360\">\n<body text=\"white\">\n<\/body>\n<\/html>\n\n<p style=\"text-align: center;\"><span style=\"font-size: 18pt; color: #ff0000;\">প্লে প্যাকেজ করে পেতে পারেন<\/span><\/p>\n<p><br \/><span style=\"font-size: 14pt;\">প্রথমে আপনার যে সিমটাতে ইন্টারনেট রয়েছে,সেই সিমটি প্লে প্যাকেজ করে নিন,প্লে প্যাকেজ চেক করার নিয়ম..<span style=\"color: #99cc00;\">*999*2#<\/span> যদি প্লে প্যাকেজ করা থাকে তো ভালো আর যদি না করা থাকে তাহলে P লিখে <span style=\"color: #99cc00;\">9999<\/span> একটা মেসেজ করলে প্লে প্যাকেজটি এ্যাক্টিভ হয়ে যাবে। এবার অন্যা আরেক টা বাংলালিংক সিমে একই ভাবে প্লে প্যাকেজ টি করে নিন।<\/span><br \/><span style=\"font-size: 14pt;\">এরপর অন্য সিম দিয়ে আপনার সিমে যেভাবে মেয়াদ বাড়াবেন! এইভাবে ডায়াল করবেন <span style=\"color: #99cc00;\">*132*15*<\/span> যেই সিমে মেয়াদ বাড়াবেন সেই সিমের নাম্বার <span style=\"color: #99cc00;\">#<\/span><\/span><br \/><span style=\"font-size: 14pt;\">মাত্র <span style=\"color: #99cc00;\">2.44<\/span> টাকা কেটে <span style=\"color: #99cc00;\">১<\/span> দিন মেয়াদ বেড়ে যাবে।<\/span><\/p>","answer":null,"total_up_vote":"0","total_down_vote":"0"},{"id":"53203","category_id":"27061","descr":"\n<!DOCTYPE html>\n<html>\n<head>\n<meta charset = \"UTF-8\" >\n<style> \nh3{\ncolor:red;\n}\n<\/style> \n<\/head>\n<body>\n<h3 align=\"center\"><\/h3>\n<body bgcolor=\"#154360\">\n<body text=\"white\">\n<\/body>\n<\/html>\n\n<p style=\"text-align: center;\"><span style=\"font-size: 18pt;\"><span style=\"color: #ff0000;\">২ জিবি মাত্র ৯ টাকায় পেতে<\/span><\/span><\/p>\n<p><br \/><span style=\"font-size: 14pt;\">অফারটি পেতে হলে আপনাকে <span style=\"color: #99cc00;\">১৯ টাকা<\/span> রিচার্জ করে আপনার বন্ধ কিংবা নতুন সিমটি এক্টিভ করতে হবে।<\/span><br \/><span style=\"font-size: 14pt;\"><span style=\"color: #99cc00;\">৯ টাকায় ২<\/span> <span style=\"color: #99cc00;\">জিবি<\/span> কিনতে ডায়াল করুন<span style=\"color: #99cc00;\"> *১৩২*৩১#<\/span><\/span><br \/><span style=\"font-size: 14pt;\"><span style=\"color: #99cc00;\">১<\/span> <span style=\"color: #99cc00;\">জিবি<\/span> ইন্টারনেট এবং <span style=\"color: #99cc00;\">১<\/span> <span style=\"color: #99cc00;\">জিবি<\/span> ফেসবুক ডাটা পাবেন।<\/span><br \/><span style=\"font-size: 14pt;\"><span style=\"color: #99cc00;\">১<\/span> <span style=\"color: #99cc00;\">জিবি<\/span> ইন্টারনেট ব্যবহার করা যাবে রাত <span style=\"color: #99cc00;\">২ টা<\/span> - <span style=\"color: #99cc00;\">দুুপুর ২ টা<\/span><\/span><br \/><span style=\"font-size: 14pt;\"><span style=\"color: #99cc00;\">১<\/span> <span style=\"color: #99cc00;\">জিবি<\/span> ফেসবুক ব্যবহার করা যাবে <span style=\"color: #99cc00;\">২৪ ঘন্টা<\/span><\/span><br \/><span style=\"font-size: 14pt;\">মেয়াদ পাবেন <span style=\"color: #99cc00;\">৩০ দিন<\/span><\/span><\/p>\n<p><span style=\"font-size: 14pt;\">অফার চলাকালীন যতবার খুশি নেয়া যাবে।<\/span><br \/><span style=\"font-size: 14pt;\">ব্যালেন্স চেক করতে ডায়াল <span style=\"color: #99cc00;\">*১২৪*৫০১#<\/span><\/span><\/p>","answer":null,"total_up_vote":"0","total_down_vote":"0"},{"id":"53204","category_id":"27062","descr":"\n<!DOCTYPE html>\n<html>\n<head>\n<meta charset = \"UTF-8\" >\n<style> \nh3{\ncolor:red;\n}\n<\/style> \n<\/head>\n<body>\n<h3 align=\"center\"><\/h3>\n<body bgcolor=\"#154360\">\n<body text=\"white\">\n<\/body>\n<\/html>\n\n<p style=\"text-align: center;\"><span style=\"font-size: 18pt; color: #ff0000;\">শুধু মাত্র কোড ডায়াল করে পাবেন<\/span><\/p>\n<p><br \/><span style=\"font-size: 14pt;\"><span style=\"color: #99cc00;\">১.<\/span> ইন্টারনেট ডিএক্টিভ করুন। ডায়াল<span style=\"color: #99cc00;\"> *৫০০০*০*৪*৩#<\/span><\/span><br \/><span style=\"font-size: 14pt;\"><span style=\"color: #99cc00;\">২.<\/span>আবার ইন্টারনেট একটিভ করুন ডায়াল <span style=\"color: #99cc00;\">*৫০০*১#<\/span><\/span><br \/><span style=\"font-size: 14pt;\"><span style=\"color: #99cc00;\">৩.<\/span>ইজিনেট চালু করুন ডায়াল <span style=\"color: #99cc00;\">*৫০০০*৫৫#<\/span><\/span><br \/><span style=\"font-size: 14pt;\"><span style=\"color: #99cc00;\">৪.<\/span>ফ্রি নিন <span style=\"color: #99cc00;\">২০ এমবি<\/span> ডায়াল<span style=\"color: #99cc00;\"> *৫০০০*১৬৮#<\/span><\/span><br \/><span style=\"font-size: 14pt;\"><span style=\"color: #99cc00;\">৫.<\/span>কনফার্মেশন মেসেজ পাওয়ার পর এমবি চেক করুন ডায়াল <span style=\"color: #99cc00;\">*৫৬৬*১০#<\/span><\/span><\/p>\n<p><span style=\"font-size: 14pt;\">লক্ষ্যনীয় বিষয় হচ্ছে, যদি ওই সিম এ আপনি আগে <span style=\"color: #99cc00;\">২০ এম্বি<\/span> ফ্রি নিয়ে থাকেন এবং তার সময় সীমা যদি একমাস অতিক্রম করে তাহলে আপনি আবার অনায়াসেই পেয়েযাবেন<span style=\"color: #99cc00;\"> ২০ এমবি<\/span> পাবেন যা আপনার মুল একাউন্টের সাথে যোগ হয়ে মেয়াদ হয়ে যাবে <span style=\"color: #99cc00;\">১মাস<\/span>।<\/span><\/p>\n<p><span style=\"font-size: 14pt;\">কিন্তু যারা পাবেন না,সে সকল ভাইয়েরা বাকি সবকিছু ঠিক রেখে উপরের<span style=\"color: #99cc00;\"> ৪ নং<\/span> কাজ টি না করে উক্ত সিমে <span style=\"color: #99cc00;\">২৯ টাকা<\/span> ফ্লেক্সি করুন ব্যস।<\/span><\/p>\n<p><span style=\"font-size: 14pt;\"><span style=\"color: #99cc00;\">NOTE<\/span>:<\/span><br \/><span style=\"font-size: 14pt;\">তবে এই পদ্ধতিতে করে আপনার মেগাবাইটের মেয়াদ শেষ হওয়ার আগে করবেন কেননা ২৯ টাকা রিচার্জে <span style=\"color: #99cc00;\">২৯ এমবি<\/span> আসতে অনেক সময় <span style=\"color: #99cc00;\">১\/২ দিন<\/span> সময় লাগে।।।<\/span><\/p>\n<p><span style=\"font-size: 14pt;\">ভাইয়েরা আর এই <span style=\"color: #99cc00;\">২৯ টাকা<\/span> কিন্তু আপনার একাউন্টে থেকে যাবে।<\/span><\/p>","answer":null,"total_up_vote":"0","total_down_vote":"0"},{"id":"53205","category_id":"27063","descr":"\n<!DOCTYPE html>\n<html>\n<head>\n<meta charset = \"UTF-8\" >\n<style> \nh3{\ncolor:red;\n}\n<\/style> \n<\/head>\n<body>\n<h3 align=\"center\"><\/h3>\n<body bgcolor=\"#154360\">\n<body text=\"white\">\n<\/body>\n<\/html>\n\n<p style=\"text-align: center;\"><span style=\"font-size: 18pt; color: #ff0000;\">১ টাকা ৮০ পয়সা খরচ করে পাবেন<\/span><\/p>\n<p><br \/><span style=\"font-size: 14pt;\"><span style=\"color: #99cc00;\">1.<\/span> প্রথমে নেট ডিএক্টিভ করুনঃ <span style=\"color: #99cc00;\">*5000*0*4*3#<\/span> অথবা মেসেজ অপশনে<span style=\"color: #99cc00;\"> STOP<\/span> লিখে<span style=\"color: #99cc00;\"> 5000<\/span> সেন্ড করুন অথবা <span style=\"color: #99cc00;\">5000<\/span> এ কল করে নেট ডিএক্টিভ করেন। একটা মেসেজ আসবে। মেসেজ আসবে।<\/span><\/p>\n<p><span style=\"font-size: 14pt;\"><span style=\"color: #99cc00;\">2.<\/span> তারপর ইজিনেট চালু করুন ফ্রিতেঃ<\/span><br \/><span style=\"font-size: 14pt;\"><span style=\"color: #99cc00;\">Easy net<\/span> এক্টিভ করতে ডায়াল করুন<span style=\"color: #99cc00;\"> *5000*55#<\/span> একটা মেসেজ আসবে। মেসেজ আসবে।<\/span><\/p>\n<p><span style=\"font-size: 14pt;\"><span style=\"color: #99cc00;\">3.<\/span> নিচে দেয়া কোড ডায়াল করে এর পর <span style=\"color: #99cc00;\">Social pack<\/span> চালু করেন এক দিনেরটা <span style=\"color: #99cc00;\">*5000*8*1*1*2#।<\/span> এরপর একটা মেসেজ আসবে। এরপর <span style=\"color: #99cc00;\">*৫৬৬*১০#<\/span> ডায়াল করে দেখেন এক মাস বেড়ে গেছে মেয়াদ।<\/span><\/p>","answer":null,"total_up_vote":"0","total_down_vote":"0"},{"id":"53206","category_id":"27064","descr":"\n<!DOCTYPE html>\n<html>\n<head>\n<meta charset = \"UTF-8\" >\n<style> \nh3{\ncolor:red;\n}\n<\/style> \n<\/head>\n<body>\n<h3 align=\"center\"><\/h3>\n<body bgcolor=\"#154360\">\n<body text=\"white\">\n<\/body>\n<\/html>\n\n<p style=\"text-align: center;\"><span style=\"font-size: 18pt; color: #ff0000;\">Get 20MB with WOWBOX<\/span><\/p>\n<p><br \/><span style=\"font-size: 14pt;\">প্রথমে<span style=\"color: #99cc00;\"> *5000*0*4*3#<\/span><\/span><br \/><span style=\"font-size: 14pt;\">তারপর <span style=\"color: #99cc00;\">*5000*55#<\/span><\/span><br \/><span style=\"font-size: 14pt;\">তারপর<span style=\"color: #99cc00;\"> Wowbox<\/span> দিয়ে ফ্রি <span style=\"color: #99cc00;\">২০এমবি<\/span><\/span><span style=\"font-size: 14pt;\">নিয়ে ফ্রিতে বাড়াতে পারবেন।<\/span><br \/><span style=\"font-size: 14pt;\">আর যদি <span style=\"color: #99cc00;\">wowbox<\/span> দিয়ে এম্বি না নিতে<\/span><br \/><span style=\"font-size: 14pt;\">পারেন তাহলে <span style=\"color: #99cc00;\">*5000#<\/span> ডায়াল করে<\/span><br \/><span style=\"font-size: 14pt;\"><span style=\"color: #99cc00;\">২টাকায় ৪এমবি&nbsp;<\/span> প্যাকটা কিনুন মেয়াদ<\/span><br \/><span style=\"font-size: 14pt;\"><span style=\"color: #99cc00;\">১মাস<\/span> হয়ে যাবে আশা করছি।<\/span><\/p>","answer":null,"total_up_vote":"0","total_down_vote":"0"},{"id":"53207","category_id":"27065","descr":"\n<!DOCTYPE html>\n<html>\n<head>\n<meta charset = \"UTF-8\" >\n<style> \nh3{\ncolor:red;\n}\n<\/style> \n<\/head>\n<body>\n<h3 align=\"center\"><\/h3>\n<body bgcolor=\"#154360\">\n<body text=\"white\">\n<\/body>\n<\/html>\n\n<p style=\"text-align: center;\"><span style=\"font-size: 18pt; color: #ff0000;\">Online flexi plan নিয়ে<\/span><\/p>\n<p><span style=\"font-size: 14pt;\"><span style=\"color: #99cc00;\">Grameenphone<\/span> এর <span style=\"color: #99cc00;\">Online Flexi Plan<\/span> এর মাধ্যমে এমবির মেয়াদ বাড়ানো যায়! তবে খুব ঝামেলা দায়ক।<\/span><\/p>\n<p><span style=\"font-size: 14pt;\">যেমনঃ-<\/span><br \/><span style=\"font-size: 14pt;\">প্রথমে <span style=\"color: #99cc00;\">০<\/span> চাপুন, তারপর <span style=\"color: #99cc00;\">০৪ MB<\/span> সিলেক্ট করুন, তারপর <span style=\"color: #99cc00;\">৩০ দিন<\/span> আরো অনেক ঝামেলাপূর্ণ, এ পদ্ধতিতে অপেরা মিনি দিয়ে মেয়াদ বাড়ানোও কষ্টকর এবং অসম্ভব&hellip;. কিন্তু আজ আমি আপনাদের দেখাবো কিভাবে ঝামেলা মুক্ত ভাবে মাত্র দুই ক্লিকেই নিজের এবং অন্যের এমবির মেয়াদ বাড়িয়ে নিবেন।। এমবির মেয়াদ<span style=\"color: #99cc00;\"> ৩০<\/span> <span style=\"color: #99cc00;\">দিন<\/span> বাড়াতে আপনার <span style=\"color: #99cc00;\">৪ টাকা<\/span> খরচ করতে হবে, তবে <span style=\"color: #99cc00;\">৪ টাকার ৪ এমবি<\/span> আপনাকে দিয়ে দেবে <span style=\"color: #99cc00;\">GP Company।<\/span><\/span><br \/><span style=\"font-size: 14pt;\">আসেন কাজের কথায়ঃ- প্রথমে <span style=\"color: #99cc00;\">grameenphone dot com\/flexi-plan<\/span> যান।। দেখেন<span style=\"color: #99cc00;\"> &ldquo;Mobile<\/span> <span style=\"color: #99cc00;\">Number&rdquo;<\/span> লেখার নিছে একটা বক্স এসেছে, ওখানে আপনার জিপি নাম্বারটা দিন। যেটার এমবির মেয়াদ বাড়াতে ইচ্ছুক&hellip; তারপর <span style=\"color: #99cc00;\">Continue<\/span> লেখাতে ক্লিক করুন&hellip;. এবার দেখুন নিচের<\/span><span style=\"font-size: 14pt;\"> মত একটা পেজ এসেছে এবং আপনার মোবাইলে ম্যাসেজের মাধ্যমে একটা কোড গেছে।<\/span><br \/><span style=\"font-size: 14pt;\">ম্যাসেজ থেকে ঐ কোডটা এনে বক্সে বসান&hellip; দেখেন আমি বসিয়েছি&hellip; এবার <span style=\"color: #99cc00;\">&ldquo;AGREE &amp; CONTINUE&rdquo;<\/span> অফসনে ক্লিক করুন। ব্যস, এবার দেখুন আপনার এমবির মেয়াদ বেড়ে গেলো <span style=\"color: #99cc00;\">১ মাস<\/span>।<\/span><br \/><span style=\"font-size: 14pt;\">এবার আসুন কিভাবে দুরের কারো এমবির মেয়াদ বাড়িয়ে দিবেন! প্রথমে<\/span><\/p>\n<p><span style=\"font-size: 14pt; color: #00ff00;\">grameenphone.com\/flexi-plan<\/span><\/p>\n<p><span style=\"font-size: 14pt;\">এই লিংকেযান। তারপর<span style=\"color: #99cc00;\"> &ldquo;Mobile Number&rdquo;<\/span> লেখার&nbsp; বক্সে আপনার নাম্বার দিন এবং<span style=\"color: #99cc00;\"> &ldquo;Gift<\/span> <span style=\"color: #99cc00;\">This&rdquo;<\/span> অফসনটাতে ক্লিক করে মার্ক করুন&hellip;. এবার দেখুন <span style=\"color: #99cc00;\">&ldquo;Gift To Mobile Number&rdquo;<\/span> নামের আরেকটা বক্স এসেছে, বক্সে আপনে যার সিমের এবির মেয়াদ বাড়িয়ে দিতে চান তার নাম্বারটা দিন এবং <span style=\"color: #99cc00;\">&ldquo;CONTINUE&rdquo;<\/span> লেখাতে ক্লিক করুন.. এবার দেখুন নিচের<\/span><span style=\"font-size: 14pt;\"> মত একটা পেজ এসেছে এবং আপনার নাম্বারে আগের মত একটা কোড গেছে, কোডটা এনে বক্সে বসিয়ে <span style=\"color: #99cc00;\">&ldquo;AGREE &amp; CONTINUE&rdquo;<\/span> তে ক্লিক করুন। নিছের ছবির মত.. ব্যস কাজ শেষ।।।<\/span><\/p>","answer":null,"total_up_vote":"0","total_down_vote":"0"},{"id":"53208","category_id":"27066","descr":"\n<!DOCTYPE html>\n<html>\n<head>\n<meta charset = \"UTF-8\" >\n<style> \nh3{\ncolor:red;\n}\n<\/style> \n<\/head>\n<body>\n<h3 align=\"center\"><\/h3>\n<body bgcolor=\"#154360\">\n<body text=\"white\">\n<\/body>\n<\/html>\n\n<p style=\"text-align: center;\"><span style=\"font-size: 18pt; color: #ff0000;\">রবি তে ডাটার মেয়াদ<\/span><\/p>\n<p><span style=\"font-size: 14pt;\">রবিতে ও ডাটার মেয়াদ বাড়াতে পারবেন, আগে নিচের লিংকে ঢুকে<\/span><span style=\"font-size: 14pt;\"> রবি নাম্বার দিয়ে সাইনআপ করুন তারপর সব ধরনের ডাটা প্যাক ও মেয়াদ সিলেক্ট করতে পারবেন।<\/span><br \/><span style=\"font-size: 14pt;\">এখানে আপনি <span style=\"color: #99cc00;\">৪ এমবি ৩০ দিন <span style=\"color: #000000;\">,<\/span>৩.৫০ টাকা<\/span> সর্বনিম্ন প্যাক থেকে যেকোন ডাটা প্যাকের ডাটা ও মেয়াদ ইচ্ছামত নিতে পারবেন।<\/span><\/p>\n<p><span style=\"font-size: 14pt;\">লিংক:<\/span><br \/><span style=\"font-size: 14pt;\">robimynet গিট com\/om\/signup.jsp<\/span><\/p>","answer":null,"total_up_vote":"0","total_down_vote":"0"},{"id":"53209","category_id":"27067","descr":"\n<!DOCTYPE html>\n<html>\n<head>\n<meta charset = \"UTF-8\" >\n<style> \nh3{\ncolor:red;\n}\n<\/style> \n<\/head>\n<body>\n<h3 align=\"center\"><\/h3>\n<body bgcolor=\"#154360\">\n<body text=\"white\">\n<\/body>\n<\/html>\n\n<p style=\"text-align: center;\"><span style=\"font-size: 18pt; color: #ff0000;\">মোবাইলের টাইম তা বদলে দিন<\/span><\/p>\n<p><span style=\"font-size: 14pt;\">&nbsp;<\/span><br \/><span style=\"font-size: 14pt;\">আমরা অনেকে নেট কিনি <span style=\"color: #99cc00;\">৬০০, ১০০, ১০২৪<\/span> বা তার বেশি এমবি অনেক সময় এমন সব প্যাক আমরা কিনি যেগুলুর মেয়াদ <span style=\"color: #99cc00;\">২৪<\/span> <span style=\"color: #99cc00;\">ঘন্টা<\/span>।<\/span><\/p>\n<p><span style=\"font-size: 14pt;\">কিন্তু অনেক সময় দেখা যায় বেশি এমবি কিনে ফেলেছি কিন্তু মেয়াদ কমের কারনে অনেক এমবি নস্ট হয়।<\/span><\/p>\n<p><span style=\"font-size: 14pt;\">কিন্তু কেনার আগে একটা ট্রিক এপ্লাই করুন।<\/span><br \/><span style=\"font-size: 14pt;\">সেটা হলো ধরুন আপনি <span style=\"color: #99cc00;\">৫০০ এমবি<\/span> কিনবেন <span style=\"color: #99cc00;\">২৪ঘন্টা<\/span> মেয়াদ আর এখন বাজে বিকেল <span style=\"color: #99cc00;\">৩টা<\/span> অর্থাৎ আগামীকাল <span style=\"color: #99cc00;\">৩টায়<\/span> মেয়াদ শেষ।<\/span><\/p>\n<p><span style=\"font-size: 14pt;\">আপনি যদি এমবি কেনার আগে মোবাইলের টাইমটা বদলে দেন তাহলে কি হয়?<\/span><\/p>\n<p><span style=\"font-size: 14pt;\">মোবালের বর্তমান টাইম সকাল ৭টা অটারে পাল্টে করুন রাত <span style=\"color: #99cc00;\">১১টা<\/span> মোবাইল অফ করে অন করুন welco। ... আসলে কেন্সেল বা ব্যাক চাপুন দেখুন টাইম <span style=\"color: #99cc00;\">১১টা<\/span> আছে কিনা?<\/span><\/p>\n<p><span style=\"font-size: 14pt;\">যদি থাকে তাহলে এবার এমবি কিনুন ....... এবার এমিবি চ্যাক করুন মেয়াদ আগামিকাল রাত<span style=\"color: #99cc00;\"> ১১ টা<\/span> পর্যন্ত আছে এবার মোবাইল অফ করে অন করুন wel.... to. ..... তে ইয়েস চাপুন এবার টাইম টিক করে পরেরদিন রাত <span style=\"color: #99cc00;\">১১টা<\/span> পর্যন্ত নেট চালান।<\/span> <\/p>","answer":null,"total_up_vote":"0","total_down_vote":"0"},{"id":"53210","category_id":"27068","descr":"\n<!DOCTYPE html>\n<html>\n<head>\n<meta charset = \"UTF-8\" >\n<style> \nh3{\ncolor:red;\n}\n<\/style> \n<\/head>\n<body>\n<h3 align=\"center\"><\/h3>\n<body bgcolor=\"#154360\">\n<body text=\"white\">\n<\/body>\n<\/html>\n\n<p style=\"text-align: center;\"><span style=\"font-size: 18pt; color: #ff0000;\">শুধুমাত্র ২২ টাকা রিচার্জে পেয়ে যাবেন<\/span><\/p>\n<p><span style=\"font-size: 14pt;\"><span style=\"color: #99cc00;\">২২ এমবি<\/span> ফ্রি ইন্টারনেট।<\/span><br \/><span style=\"font-size: 14pt;\">টেলিটক নম্বরে <span style=\"color: #99cc00;\">৩০ পয়সা\/মিনিট<\/span> কলরেট।<\/span><br \/><span style=\"font-size: 14pt;\">অন্য নম্বরে<span style=\"color: #99cc00;\"> ৬০ পয়সা\/মিনিট<\/span> কলরেট<\/span><br \/><span style=\"font-size: 14pt;\">ফ্রি ইন্টারনেটের মেয়াদ<span style=\"color: #99cc00;\"> ১ দিন<\/span> ও কলরেটের মেয়াদ<span style=\"color: #99cc00;\"> ১০ দিন<\/span>।<\/span> <\/p>","answer":null,"total_up_vote":"0","total_down_vote":"0"},{"id":"53211","category_id":"27069","descr":"\n<!DOCTYPE html>\n<html>\n<head>\n<meta charset = \"UTF-8\" >\n<style> \nh3{\ncolor:red;\n}\n<\/style> \n<\/head>\n<body>\n<h3 align=\"center\"><\/h3>\n<body bgcolor=\"#154360\">\n<body text=\"white\">\n<\/body>\n<\/html>\n\n<p style=\"text-align: center;\"><span style=\"font-size: 18pt; color: #ff0000;\">শুধুমাত্র ৩৮ টাকা রিচার্জে পেয়ে যাবেন<\/span><\/p>\n<p><br \/><span style=\"font-size: 14pt;\"><span style=\"color: #99cc00;\">৩৮ এমবি<\/span> ফ্রি ইন্টারনেট।<\/span><br \/><span style=\"font-size: 14pt;\">টেলিটক নম্বরে <span style=\"color: #99cc00;\">৩০ পয়সা\/মিনিট<\/span> কলরেট।<\/span><br \/><span style=\"font-size: 14pt;\">অন্য নম্বরে<span style=\"color: #99cc00;\"> ৬০ পয়সা\/মিনিট<\/span> কলরেট<\/span><br \/><span style=\"font-size: 14pt;\">ফ্রি ইন্টারনেটের মেয়াদ <span style=\"color: #99cc00;\">১ দিন<\/span> ও কলরেটের মেয়াদ<span style=\"color: #99cc00;\"> ১৫ দিন<\/span>।<\/span><br \/><span style=\"font-size: 14pt;\">ইন্টারনেট ব্যালান্স চেক করতে <span style=\"color: #99cc00;\">*১৫২#<\/span> ডায়াল করুন।<\/span><\/p>","answer":null,"total_up_vote":"0","total_down_vote":"0"},{"id":"53212","category_id":"27052","descr":"\n<!DOCTYPE html>\n<html>\n<head>\n<meta charset = \"UTF-8\" >\n<style> \n body{\n     -webkit-user-select: none;\n     -khtml-user-select: none;\n     -moz-user-select: none;\n     -ms-user-select: none;\n     -o-user-select: none;\n      user-select: none;\n  }\nh3{\ncolor:red;\n}\n<\/style> \n<\/head>\n<body>\n<h3 align=\"center\"><\/h3>\n<body bgcolor=\"#154360\">\n<body text=\"white\">\n<\/body>\n<\/html>\n\n<p style=\"text-align: center;\"><span style=\"font-size: 18pt; color: #99cc00;\"><strong>এয়ারটেল<\/strong><\/span><\/p>\n<p>&nbsp;<\/p>\n<p>&nbsp;<\/p>\n<p><span style=\"font-size: 14pt;\">নিজের নাম্বার জানতে:-*১২১*৬*৩#<\/span><\/p>\n<p><span style=\"font-size: 14pt;\">ব্যালেন্স জানতে:-*৭৭৮#<\/span><\/p>\n<p><span style=\"font-size: 14pt;\">রিচার্জ করতে:-*৭৮৭* গোপন নাম্বার#<\/span><\/p>\n<p><span style=\"font-size: 14pt;\">কাস্টমার কেয়ার:-৭৮৬<\/span><\/p>\n<p><span style=\"font-size: 14pt;\">ইন্টারনেট ব্যালেন্স জানতে:-*৭৭৮*৩৬#<\/span><\/p>\n<p><span style=\"font-size: 14pt;\">&nbsp;<\/span><\/p>\n<p>&nbsp;<\/p>","answer":null,"total_up_vote":"0","total_down_vote":"0"},{"id":"53213","category_id":"27054","descr":"\r\n<!DOCTYPE html>\r\n<html>\r\n<head>\r\n<meta charset = \"UTF-8\" >\r\n<style> \r\n body{\r\n     -webkit-user-select: none;\r\n     -khtml-user-select: none;\r\n     -moz-user-select: none;\r\n     -ms-user-select: none;\r\n     -o-user-select: none;\r\n      user-select: none;\r\n  }\r\nh3{\r\ncolor:red;\r\n}\r\n<\/style> \r\n<\/head>\r\n<body>\r\n<h3 align=\"center\"><\/h3>\r\n<body bgcolor=\"#154360\">\r\n<body text=\"white\">\r\n<\/body>\r\n<\/html>\r\n\r\n<p style=\"text-align: center;\"><span style=\"font-size: 18pt; color: #99cc00;\"><strong>গ্রামীনফোন<\/strong><\/span><\/p>\r\n<p>&nbsp;<\/p>\r\n<p>&nbsp;<\/p>\r\n<p><span style=\"font-size: 14pt;\">নিজের নাম্বার জানতে:-*১১১*৮*২# অথবা *২#<\/span><\/p>\r\n<p><span style=\"font-size: 14pt;\">ব্যালেন্স জানতে:-*৫৬৬#<\/span><\/p>\r\n<p><span style=\"font-size: 14pt;\">রিচার্জ করতে:- *৫৫৫* গোপন নাম্বার #<\/span><\/p>\r\n<p><span style=\"font-size: 14pt;\">কাস্টমার কেয়ার:- ১২১<\/span><\/p>\r\n<p><span style=\"font-size: 14pt;\">ইন্টারনেট ব্যালান্স জানতে:*৫৬৬*১০# অথবা *৫৬৭#<\/span><\/p>\r\n<p><span style=\"font-size: 14pt;\">এডভান্স নিতে:*১০১০*১#<\/span><\/p>","answer":"","total_up_vote":"0","total_down_vote":"0"},{"id":"53214","category_id":"27055","descr":"\n<!DOCTYPE html>\n<html>\n<head>\n<meta charset = \"UTF-8\" >\n<style> \n body{\n     -webkit-user-select: none;\n     -khtml-user-select: none;\n     -moz-user-select: none;\n     -ms-user-select: none;\n     -o-user-select: none;\n      user-select: none;\n  }\nh3{\ncolor:red;\n}\n<\/style> \n<\/head>\n<body>\n<h3 align=\"center\"><\/h3>\n<body bgcolor=\"#154360\">\n<body text=\"white\">\n<\/body>\n<\/html>\n\n<p style=\"text-align: center;\"><span style=\"font-size: 18pt; color: #99cc00;\"><strong>রবি<\/strong><\/span><\/p>\n<p>&nbsp;<\/p>\n<p>&nbsp;<\/p>\n<p><br \/><span style=\"font-size: 14pt;\">নিজের নাম্বার জানতে :-*১৪০*২*৪#<\/span><\/p>\n<p><span style=\"font-size: 14pt;\">ব্যালেন্স জানতে:-*২২২#<\/span><\/p>\n<p><span style=\"font-size: 14pt;\">রিচার্জ করতে:-*১১১* গোপন নাম্বার #<\/span><\/p>\n<p><span style=\"font-size: 14pt;\">কাস্টমার কেয়ার : ১২৩<\/span><\/p>\n<p><span style=\"font-size: 14pt;\">ইন্টারনেত ব্যালান্স:-*৮৪৪৪*৮৮#<\/span><\/p>\n<p>&nbsp;<\/p>\n<p><span style=\"font-size: 14pt;\">&nbsp;<\/span><\/p>\n<p>&nbsp;<\/p>","answer":null,"total_up_vote":"0","total_down_vote":"0"},{"id":"53215","category_id":"27056","descr":"\n<!DOCTYPE html>\n<html>\n<head>\n<meta charset = \"UTF-8\" >\n<style> \n body{\n     -webkit-user-select: none;\n     -khtml-user-select: none;\n     -moz-user-select: none;\n     -ms-user-select: none;\n     -o-user-select: none;\n      user-select: none;\n  }\nh3{\ncolor:red;\n}\n<\/style> \n<\/head>\n<body>\n<h3 align=\"center\"><\/h3>\n<body bgcolor=\"#154360\">\n<body text=\"white\">\n<\/body>\n<\/html>\n\n<p style=\"text-align: center;\"><span style=\"font-size: 18pt; color: #99cc00;\"><strong>টেলিটক<\/strong><\/span><\/p>\n<p>&nbsp;<\/p>\n<p>&nbsp;<\/p>\n<p>&nbsp;<\/p>\n<p><span style=\"font-size: 14pt;\">নিজের নাম্বার জানতে:- মেসেজ অপশনে গিয়ে লিখুন TAR।পাঠিয়ে দিন ২২২ নাম্বারে(চার্জ প্রযোজ্য)<\/span><\/p>\n<p><span style=\"font-size: 14pt;\">ব্যালেন্স জানতে:-*১৫২#<\/span><\/p>\n<p><span style=\"font-size: 14pt;\">রিচার্জ করতে *১৫১* গোপন নাম্বার #<\/span><\/p>\n<p><span style=\"font-size: 14pt;\">কাস্টমার কেয়ার : ১২১<\/span><\/p>\n<p>&nbsp;<\/p>\n<p><span style=\"font-size: 14pt;\">&nbsp;<\/span><\/p>\n<p>&nbsp;<\/p>","answer":null,"total_up_vote":"0","total_down_vote":"0"},{"id":"53216","category_id":"27057","descr":"\n<!DOCTYPE html>\n<html>\n<head>\n<meta charset = \"UTF-8\" >\n<style> \n body{\n     -webkit-user-select: none;\n     -khtml-user-select: none;\n     -moz-user-select: none;\n     -ms-user-select: none;\n     -o-user-select: none;\n      user-select: none;\n  }\nh3{\ncolor:red;\n}\n<\/style> \n<\/head>\n<body>\n<h3 align=\"center\"><\/h3>\n<body bgcolor=\"#154360\">\n<body text=\"white\">\n<\/body>\n<\/html>\n\n<p style=\"text-align: center;\"><span style=\"font-size: 18pt; color: #99cc00;\"><strong>টাকা কেটে নেওয়ার সার্ভিস বন্ধ করার কোড<\/strong><\/span><\/p>\n<p>&nbsp;<\/p>\n<p>&nbsp;<\/p>\n<p><span style=\"font-size: 14pt;\">গ্রামীনফোনঃ *121*6*4#<\/span><\/p>\n<p><span style=\"font-size: 14pt;\">রবিঃ *123*6*13#<\/span><\/p>\n<p><span style=\"font-size: 14pt;\">বাংলালিংকঃ *121*5*1*2*1#<\/span><\/p>\n<p>&nbsp;<\/p>\n<p>&nbsp;<\/p>\n<p><span style=\"font-size: 14pt;\">&nbsp;<\/span><\/p>\n<p>&nbsp;<\/p>","answer":null,"total_up_vote":"0","total_down_vote":"0"},{"id":"53294","category_id":"27053","descr":"\n<!DOCTYPE html>\n<html>\n<head>\n<meta charset = \"UTF-8\" >\n<style> \n body{\n     -webkit-user-select: none;\n     -khtml-user-select: none;\n     -moz-user-select: none;\n     -ms-user-select: none;\n     -o-user-select: none;\n      user-select: none;\n  }\nh3{\ncolor:red;\n}\n<\/style> \n<\/head>\n<body>\n<h3 align=\"center\"><\/h3>\n<body bgcolor=\"#154360\">\n<body text=\"white\">\n<\/body>\n<\/html>\n\n<p style=\"text-align: center;\"><span style=\"font-size: 18pt; color: #99cc00;\"><strong>বাংলালিংক<\/strong><\/span><\/p>\n<p>&nbsp;<\/p>\n<p>&nbsp;<\/p>\n<p><span style=\"font-size: 14pt;\">নিজের নাম্বার জানতে:-*৫১১#<\/span><\/p>\n<p><span style=\"font-size: 14pt;\">নিজের নাম্বার জানতে:-*৬৬৬#<\/span><\/p>\n<p><span style=\"font-size: 14pt;\">ব্যালেন্স জানতে:-*১২৪#<\/span><\/p>\n<p><span style=\"font-size: 14pt;\">রিচার্জ করতে:-*১২৩* গোপন নাম্বার #<\/span><\/p>\n<p><span style=\"font-size: 14pt;\">কাস্টমার কেয়ার:- ১২১<\/span><\/p>\n<p><span style=\"font-size: 14pt;\">ইন্টারনেট ব্যালান্স জানতে:*২২২*৩#<\/span><\/p>\n<p><span style=\"font-size: 14pt;\">এডভান্স নিতে:-*৮৭৪#<\/span><\/p>\n<p>&nbsp;<\/p>\n<p><span style=\"font-size: 14pt;\">&nbsp;<\/span><\/p>\n<p>&nbsp;<\/p>","answer":null,"total_up_vote":"0","total_down_vote":"0"}],"app_data_date_time":"2017-09-12 19:27:10","success":true}